[
  {
    "timestamp": "2026-02-22T22:09:52.109Z",
    "actor": "ConversationLevelDesignerAgent",
    "action": "parse_specification",
    "description": "Convert natural language to LevelPlan.json",
    "specPath": "executions/5b669ba0-fa0c-42f0-9e28-2bf1fea77b3c/steps/003524d0-b1ec-4e28-b374-5f3f23136824.json"
  },
  {
    "timestamp": "2026-02-22T22:09:54.877Z",
    "actor": "UnrealLevelBuilderAgent",
    "action": "generate_level",
    "description": "Create blockout geometry in Unreal Engine",
    "specPath": "executions/5b669ba0-fa0c-42f0-9e28-2bf1fea77b3c/steps/2ea30a11-e2c5-406d-9d04-d5544d7801d9.json"
  },
  {
    "timestamp": "2026-02-22T22:09:56.535Z",
    "actor": "GameplaySystemsAgent",
    "action": "implement_gameplay",
    "description": "Add objectives, spawn points, and game rules",
    "specPath": "executions/5b669ba0-fa0c-42f0-9e28-2bf1fea77b3c/steps/235da529-4cd0-445c-ace9-a54f1c408031.json"
  }
]