[
  {
    "timestamp": "2026-02-22T22:10:05.228Z",
    "actor": "TechArtVFXAudioAgent",
    "action": "generate_placeholder",
    "description": "Create Tier 1 placeholder assets from concept art",
    "specPath": "executions/aa7f1bba-d52b-4ffa-8a4c-c431cc22aa23/steps/c4a71bd0-b9f3-4ffb-9521-2fdb40d8d5ad.json"
  },
  {
    "timestamp": "2026-02-22T22:10:06.819Z",
    "actor": "AssetPipelineAgent",
    "action": "import_assets",
    "description": "Import generated assets into Unreal project",
    "specPath": "executions/aa7f1bba-d52b-4ffa-8a4c-c431cc22aa23/steps/9892ffdc-bd43-4bed-acf3-696b04282275.json"
  }
]