[
  {
    "timestamp": "2026-01-31T23:38:09.082Z",
    "actor": "ConversationLevelDesignerAgent",
    "action": "parse_specification",
    "description": "Convert natural language to LevelPlan.json",
    "specPath": "executions/c6f4f1e0-ebee-487c-8d07-e835767ed86f/steps/f5710bc7-c354-46a2-b631-103b2afe2d8d.json"
  },
  {
    "timestamp": "2026-01-31T23:38:11.831Z",
    "actor": "UnrealLevelBuilderAgent",
    "action": "generate_level",
    "description": "Create blockout geometry in Unreal Engine",
    "specPath": "executions/c6f4f1e0-ebee-487c-8d07-e835767ed86f/steps/d752a8ad-8b85-403d-9fe9-550c6af64fc5.json"
  },
  {
    "timestamp": "2026-01-31T23:38:14.788Z",
    "actor": "GameplaySystemsAgent",
    "action": "implement_gameplay",
    "description": "Add objectives, spawn points, and game rules",
    "specPath": "executions/c6f4f1e0-ebee-487c-8d07-e835767ed86f/steps/5161f6ae-8944-4042-8fba-2ab2d023ee91.json"
  }
]